jakopicevca2017/__init__.py
jakopicevca2017/__main__.py
jakopicevca2017/jakopicevca.py
jakopicevca2017-1.1.post0.dist-info/METADATA
jakopicevca2017-1.1.post0.dist-info/RECORD
jakopicevca2017-1.1.post0.dist-info/WHEEL
jakopicevca2017-1.1.post0.dist-info/entry_points.txt
jakopicevca2017-1.1.post0.dist-info/top_level.txt
